{
    "@context": {
        "@vocab": "http://example.org/local#",
        "kb": "http://example.org/kb/",
        "uco-core": "https://ontology.unifiedcyberontology.org/uco/core/",
        "uco-observable": "https://ontology.unifiedcyberontology.org/uco/observable/",
        "uco-types": "https://ontology.unifiedcyberontology.org/uco/types/",
        "uco-vocabulary": "https://ontology.unifiedcyberontology.org/uco/vocabulary/",
        "xsd": "http://www.w3.org/2001/XMLSchema#"
    },
    "@graph": [
        {
            "@id": "kb:extracted_email_address-8a042a47-e34b-46e3-b5a2-0fac4fd66aa7",
            "@type": "uco-observable:EmailAddress",
            "uco-core:hasFacet": [
                {
                    "@id": "kb:content-data-facet-ccebaca3-4485-46d8-bdf2-d2905a08d0c9",
                    "@type": "uco-observable:ContentDataFacet",
                    "uco-observable:byteOrder": {
                        "@type": "uco-vocabulary:EndiannessTypeVocab",
                        "@value": "Big-endian"
                    },
                    "uco-observable:sizeInBytes": 17,
                    "uco-observable:dataPayload": "bmVsc29uQGNyeW53ci5jb20=",
                    "uco-observable:hash": [
                        {
                            "@id": "kb:hash-f9eebfa7-ce0e-513f-b4be-f3fe7512c79a",
                            "@type": "uco-types:Hash",
                            "uco-types:hashMethod": {
                                "@type": "uco-vocabulary:HashNameVocab",
                                "@value": "SHA256"
                            },
                            "uco-types:hashValue": {
                                "@type": "xsd:hexBinary",
                                "@value": "8fabebdaf41b54014f6c3507c44ae160547d05d31bd50d6a12234c5bc4bdb45c"
                            }
                        }
                    ]
                }
            ]
        },
        {
            "@id": "kb:relationship-c8007a4a-46b3-4fbb-8b67-7a14b9e65694",
            "@type": "uco-observable:ObservableRelationship",
            "uco-core:source": {
                "@id": "kb:extracted_email_address-8a042a47-e34b-46e3-b5a2-0fac4fd66aa7"
            },
            "uco-core:target": {
                "@id": "kb:decompressed_gzip-95bfe9c0-1473-41e0-a2b4-22dd2d28bd8b"
            },
            "uco-core:kindOfRelationship": "Contained_Within",
            "uco-core:isDirectional": true,
            "uco-core:hasFacet": [
                {
                    "@id": "kb:data-range-facet-e32acbee-abfe-4739-9ddb-7e60cbb82ec7",
                    "@type": "uco-observable:DataRangeFacet",
                    "uco-observable:rangeOffset": 1600,
                    "uco-observable:rangeSize": 17
                }
            ]
        },
        {
            "@id": "kb:extracted_email_address-416ecb32-ecb1-4e23-a5b4-836c07a1de4e",
            "@type": "uco-observable:EmailAddress",
            "uco-core:hasFacet": [
                {
                    "@id": "kb:content-data-facet-fa866136-c537-4b25-a481-364c7859f8f0",
                    "@type": "uco-observable:ContentDataFacet",
                    "uco-observable:byteOrder": {
                        "@type": "uco-vocabulary:EndiannessTypeVocab",
                        "@value": "Big-endian"
                    },
                    "uco-observable:sizeInBytes": 15,
                    "uco-observable:dataPayload": "c3Rya0BrZXliaXQubmV0",
                    "uco-observable:hash": [
                        {
                            "@id": "kb:hash-59bd11fd-af49-5e39-ba3b-54ba31f3c8d6",
                            "@type": "uco-types:Hash",
                            "uco-types:hashMethod": {
                                "@type": "uco-vocabulary:HashNameVocab",
                                "@value": "SHA256"
                            },
                            "uco-types:hashValue": {
                                "@type": "xsd:hexBinary",
                                "@value": "9a6c11d66829bf429efe5ef4c066d50272394481cc3f8ae8116a006c81dc6cf9"
                            }
                        }
                    ]
                }
            ]
        },
        {
            "@id": "kb:relationship-21bf5cd2-2365-420d-8175-a87fd722e790",
            "@type": "uco-observable:ObservableRelationship",
            "uco-core:source": {
                "@id": "kb:extracted_email_address-416ecb32-ecb1-4e23-a5b4-836c07a1de4e"
            },
            "uco-core:target": {
                "@id": "kb:decompressed_gzip-95bfe9c0-1473-41e0-a2b4-22dd2d28bd8b"
            },
            "uco-core:kindOfRelationship": "Contained_Within",
            "uco-core:isDirectional": true,
            "uco-core:hasFacet": [
                {
                    "@id": "kb:data-range-facet-dae28d94-d202-43d9-96e7-62c32ee26a9f",
                    "@type": "uco-observable:DataRangeFacet",
                    "uco-observable:rangeOffset": 16095,
                    "uco-observable:rangeSize": 15
                }
            ]
        },
        {
            "@id": "kb:decompressed_gzip-95bfe9c0-1473-41e0-a2b4-22dd2d28bd8b",
            "@type": "uco-observable:ContentData",
            "uco-core:hasFacet": [
                {
                    "@id": "kb:content-data-facet-ed051828-45e7-47b3-82ca-be5b9a88d5f7",
                    "@type": "uco-observable:ContentDataFacet",
                    "uco-observable:byteOrder": {
                        "@type": "uco-vocabulary:EndiannessTypeVocab",
                        "@value": "Big-endian"
                    },
                    "uco-observable:magicNumber": "H4s=",
                    "uco-observable:mimeType": "application/x-compressed",
                    "uco-observable:sizeInBytes": 17605,
                    "uco-observable:hash": [
                        {
                            "@id": "kb:hash-7a2f290f-2944-5520-816a-85f722e64525",
                            "@type": "uco-types:Hash",
                            "uco-types:hashMethod": {
                                "@type": "uco-vocabulary:HashNameVocab",
                                "@value": "SHA256"
                            },
                            "uco-types:hashValue": {
                                "@type": "xsd:hexBinary",
                                "@value": "8c8b39473c4064f6b4db11a67251ffdf65c42ebadc5c3e02a009f95f6cf7c9e8"
                            }
                        }
                    ]
                }
            ]
        },
        {
            "@id": "kb:relationship-a99e82ff-3908-41ea-b5db-71858d651476",
            "@type": "uco-observable:ObservableRelationship",
            "uco-core:source": {
                "@id": "kb:decompressed_gzip-95bfe9c0-1473-41e0-a2b4-22dd2d28bd8b"
            },
            "uco-core:target": {
                "@id": "kb:compressed_gzip-56ce1a82-7965-4a50-8feb-7524e03fba04"
            },
            "uco-core:kindOfRelationship": "Decompressed_From",
            "uco-core:isDirectional": true,
            "uco-core:hasFacet": [
                {
                    "@id": "kb:compressed-stream-facet-87861bfc-a11c-4b26-a6ec-0216df139202",
                    "@type": "uco-observable:CompressedStreamFacet",
                    "uco-observable:compressionMethod": "GZIP"
                }
            ]
        },
        {
            "@id": "kb:compressed_gzip-56ce1a82-7965-4a50-8feb-7524e03fba04",
            "@type": "uco-observable:ContentData",
            "uco-core:hasFacet": [
                {
                    "@id": "kb:content-data-facet-6e51c0f0-8a00-4b71-8315-f413638cc9ad",
                    "@type": "uco-observable:ContentDataFacet",
                    "uco-observable:sizeInBytes": 4598,
                    "uco-observable:dataPayload": "<base 64 encoded data of the file>",
                    "uco-observable:hash": [
                        {
                            "@id": "kb:hash-47323085-5f5a-5252-82b3-347183525558",
                            "@type": "uco-types:Hash",
                            "uco-types:hashMethod": {
                                "@type": "uco-vocabulary:HashNameVocab",
                                "@value": "SHA256"
                            },
                            "uco-types:hashValue": {
                                "@type": "xsd:hexBinary",
                                "@value": "a665a45920422f9d417e4867efdc4fb8a04a1f3fff1fa07e998e86f7f7a27ae3"
                            }
                        }
                    ]
                }
            ]
        },
        {
            "@id": "kb:relationship-58b547f5-65a5-4275-84d7-32a234f4aba0",
            "@type": "uco-observable:ObservableRelationship",
            "uco-core:source": {
                "@id": "kb:compressed_gzip-56ce1a82-7965-4a50-8feb-7524e03fba04"
            },
            "uco-core:target": {
                "@id": "kb:decompressed_gzip-93aef5ce-40a5-4bd4-8a4f-56f885d27695"
            },
            "uco-core:kindOfRelationship": "Contained_Within",
            "uco-core:isDirectional": true,
            "uco-core:hasFacet": [
                {
                    "@id": "kb:data-range-facet-a2eed443-4b4b-4998-97d5-091b67753b9f",
                    "@type": "uco-observable:DataRangeFacet",
                    "uco-observable:rangeOffset": 64000,
                    "uco-observable:rangeSize": 45988
                }
            ]
        },
        {
            "@id": "kb:decompressed_gzip-93aef5ce-40a5-4bd4-8a4f-56f885d27695",
            "@type": "uco-observable:ContentData",
            "uco-core:hasFacet": [
                {
                    "@id": "kb:content-data-facet-60001b4f-081e-4b2d-a1a1-bf7664f3df58",
                    "@type": "uco-observable:ContentDataFacet",
                    "uco-observable:sizeInBytes": 54564465,
                    "uco-observable:dataPayload": "<base 64 encoded data of the file>",
                    "uco-observable:hash": [
                        {
                            "@id": "kb:hash-9c9f1145-243a-58d6-b420-bd38101cb511",
                            "@type": "uco-types:Hash",
                            "uco-types:hashMethod": {
                                "@type": "uco-vocabulary:HashNameVocab",
                                "@value": "SHA256"
                            },
                            "uco-types:hashValue": {
                                "@type": "xsd:hexBinary",
                                "@value": "03ac674216f3e15c761ee1a5e255f067953623c8b388b4459e13f978d7c846f4"
                            }
                        }
                    ]
                }
            ]
        },
        {
            "@id": "kb:relationship-c128681a-49ab-4b98-8535-e338132a795d",
            "@type": "uco-observable:ObservableRelationship",
            "uco-core:source": {
                "@id": "kb:decompressed_gzip-93aef5ce-40a5-4bd4-8a4f-56f885d27695"
            },
            "uco-core:target": {
                "@id": "kb:compressed_gzip-e17babc0-dabb-45d1-8202-0f02518c2a89"
            },
            "uco-core:kindOfRelationship": "Decompressed_From",
            "uco-core:isDirectional": true,
            "uco-core:hasFacet": [
                {
                    "@id": "kb:compressed-stream-facet-c3131617-2a09-4f11-b051-8cd80dbf9139",
                    "@type": "uco-observable:CompressedStreamFacet",
                    "uco-observable:compressionMethod": "GZIP"
                }
            ]
        },
        {
            "@id": "kb:compressed_gzip-e17babc0-dabb-45d1-8202-0f02518c2a89",
            "@type": "uco-observable:ContentData",
            "uco-core:hasFacet": [
                {
                    "@id": "kb:content-data-facet-a9e59f58-4ed3-40f4-8500-6b9d27cf72a1",
                    "@type": "uco-observable:ContentDataFacet",
                    "uco-observable:sizeInBytes": 23564465,
                    "uco-observable:dataPayload": "<base 64 encoded data of the file>",
                    "uco-observable:hash": [
                        {
                            "@id": "kb:hash-84b82467-019e-53cf-a1e6-e8a394379916",
                            "@type": "uco-types:Hash",
                            "uco-types:hashMethod": {
                                "@type": "uco-vocabulary:HashNameVocab",
                                "@value": "SHA256"
                            },
                            "uco-types:hashValue": {
                                "@type": "xsd:hexBinary",
                                "@value": "5994471abb01112afcc18159f6cc74b4f511b99806da59b3caf5a9c173cacfc5"
                            }
                        }
                    ]
                }
            ]
        },
        {
            "@id": "kb:relationship-4b3f030f-c214-48a8-9832-c302994d1874",
            "@type": "uco-observable:ObservableRelationship",
            "uco-core:source": {
                "@id": "kb:compressed_gzip-e17babc0-dabb-45d1-8202-0f02518c2a89"
            },
            "uco-core:target": {
                "@id": "kb:disk_image-f654431a-ee73-4c9f-8ebb-e689df534f6c"
            },
            "uco-core:kindOfRelationship": "Contained_Within",
            "uco-core:isDirectional": true,
            "uco-core:hasFacet": [
                {
                    "@id": "kb:data-range-facet-9dcf3fa6-492d-42ed-8b64-d0c9159e0725",
                    "@type": "uco-observable:DataRangeFacet",
                    "uco-observable:rangeOffset": 946315592,
                    "uco-observable:rangeSize": 23564465
                }
            ]
        },
        {
            "@id": "kb:disk_image-f654431a-ee73-4c9f-8ebb-e689df534f6c",
            "@type": [
                "uco-observable:File",
                "uco-observable:Image"
            ],
            "uco-core:hasFacet": [
                {
                    "@id": "kb:content-data-facet-9aa48d1c-4c01-4c7d-a70e-9609eeb9eb59",
                    "@type": "uco-observable:ContentDataFacet",
                    "uco-observable:sizeInBytes": 2000000000,
                    "uco-observable:dataPayload": "<base 64 encoded data of the file>",
                    "uco-observable:hash": [
                        {
                            "@id": "kb:hash-c492a39d-88e4-51f1-9f80-31524494f877",
                            "@type": "uco-types:Hash",
                            "uco-types:hashMethod": {
                                "@type": "uco-vocabulary:HashNameVocab",
                                "@value": "SHA256"
                            },
                            "uco-types:hashValue": {
                                "@type": "xsd:hexBinary",
                                "@value": "8d969eef6ecad3c29a3a629280e686cf0c3f5d5a86aff3ca12020c923adc6c92"
                            }
                        }
                    ]
                }
            ]
        }
    ]
}
