{
    "@context": {
        "@vocab": "http://example.org/local#",
        "kb": "http://example.org/kb/",
        "uco-core": "https://ontology.unifiedcyberontology.org/uco/core/",
        "uco-identity": "https://ontology.unifiedcyberontology.org/uco/identity/",
        "uco-observable": "https://ontology.unifiedcyberontology.org/uco/observable/",
        "xsd": "http://www.w3.org/2001/XMLSchema#"
    },
    "@graph": [
        {
            "@id": "kb:att-466a0ea8-b22f-4175-8119-846bec8f7831",
            "@type": "uco-identity:Organization"
        },
        {
            "@id": "kb:sprint-68503a2e-6ec3-422a-8ef4-9f57f2aad202",
            "@type": "uco-identity:Organization"
        },
        {
            "@id": "kb:verizon-47a7bc5c-f4a7-4fe3-a700-82bcfaf07a12",
            "@type": "uco-identity:Organization"
        },
        {
            "@id": "kb:zoom-b5a12ff2-91ac-42d1-9741-7db20e50bc0b",
            "@type": "uco-identity:Organization"
        },
        {
            "@id": "kb:application-79636b28-77c9-4005-b62d-b87a233687ef",
            "@type": [
                "uco-observable:Application",
                "uco-observable:Software"
            ]
        },
        {
            "@id": "kb:application-a5378ee2-32e0-40ba-b31c-3a5c110e7a29",
            "@type": [
                "uco-observable:Application",
                "uco-observable:Software"
            ]
        },
        {
            "@id": "kb:application-b01d8144-5fa9-44e9-a5f9-668d433b6108",
            "@type": [
                "uco-observable:Application",
                "uco-observable:Software"
            ]
        },
        {
            "@id": "kb:phone_account-4e172ed5-7b58-4903-96fe-4558f46820ba",
            "@type": "uco-observable:PhoneAccount",
            "uco-core:hasFacet": [
                {
                    "@id": "kb:account-facet-03ee9e1a-3bfc-4aa9-b040-ec420293c595",
                    "@type": "uco-observable:AccountFacet",
                    "uco-observable:accountIssuer": {
                        "@id": "kb:att-466a0ea8-b22f-4175-8119-846bec8f7831"
                    },
                    "uco-observable:accountIdentifier": "AT123456890",
                    "uco-observable:isActive": true
                },
                {
                    "@id": "kb:phone-account-facet-34a688bd-59bd-4786-ba0b-226ac437607d",
                    "@type": "uco-observable:PhoneAccountFacet",
                    "uco-observable:phoneNumber": "1235551337"
                }
            ]
        },
        {
            "@id": "kb:phone_account-86bdc508-1f64-4df3-bc8f-0136976c2e93",
            "@type": "uco-observable:PhoneAccount",
            "uco-core:hasFacet": [
                {
                    "@id": "kb:account-facet-4d4de5bf-85a1-4c47-9697-4f748d23416b",
                    "@type": "uco-observable:AccountFacet",
                    "uco-observable:accountIssuer": {
                        "@id": "kb:sprint-68503a2e-6ec3-422a-8ef4-9f57f2aad202"
                    },
                    "uco-observable:accountIdentifier": "SP123456890",
                    "uco-observable:isActive": true
                },
                {
                    "@id": "kb:phone-account-facet-51d0ee2e-6152-4e81-b0cd-0291a1dbf245",
                    "@type": "uco-observable:PhoneAccountFacet",
                    "uco-observable:phoneNumber": "1234560000"
                }
            ]
        },
        {
            "@id": "kb:phone_account-19db8820-3d40-4b38-84cf-abbb26c95128",
            "@type": "uco-observable:PhoneAccount",
            "uco-core:hasFacet": [
                {
                    "@id": "kb:account-facet-386414cf-6a2b-48e0-8f84-0dfb18fbd88f",
                    "@type": "uco-observable:AccountFacet",
                    "uco-observable:accountIssuer": {
                        "@id": "kb:verizon-47a7bc5c-f4a7-4fe3-a700-82bcfaf07a12"
                    },
                    "uco-observable:accountIdentifier": "VZ123456890",
                    "uco-observable:isActive": true
                },
                {
                    "@id": "kb:phone-account-facet-b7b600a5-044b-4fad-bc5c-24c6f16fa816",
                    "@type": "uco-observable:PhoneAccountFacet",
                    "uco-observable:phoneNumber": "1235550001"
                }
            ]
        },
        {
            "@id": "kb:bridge_account-2ee6c2f5-11dd-42f4-9345-cdefc1e24889",
            "@type": "uco-observable:PhoneAccount",
            "uco-core:hasFacet": [
                {
                    "@id": "kb:account-facet-9a8815dc-e0fd-4da4-85e1-a53089c24083",
                    "@type": "uco-observable:AccountFacet",
                    "uco-observable:accountIssuer": {
                        "@id": "kb:zoom-b5a12ff2-91ac-42d1-9741-7db20e50bc0b"
                    },
                    "uco-observable:accountIdentifier": "user@example.org",
                    "uco-observable:isActive": true
                },
                {
                    "@id": "kb:phone-account-facet-67afa12a-e21a-45f4-8829-6f407d6cc1d2",
                    "@type": "uco-observable:PhoneAccountFacet",
                    "uco-observable:phoneNumber": "1235550002"
                }
            ]
        },
        {
            "@id": "kb:phone_call-edacc7ec-4e8e-4de4-ad83-10a892cd3855",
            "@type": "uco-observable:Call",
            "uco-core:description": "An example of a two-party, one-way phone call that has clear directionality between a caller (from) and receiver (to).",
            "uco-core:hasFacet": [
                {
                    "@id": "kb:call-facet-c93c0dc7-4a01-4145-9c1c-839b743fba64",
                    "@type": "uco-observable:CallFacet",
                    "uco-observable:application": {
                        "@id": "kb:application-a5378ee2-32e0-40ba-b31c-3a5c110e7a29"
                    },
                    "uco-observable:callType": "outgoing",
                    "uco-observable:startTime": {
                        "@type": "xsd:dateTime",
                        "@value": "2010-01-15T17:59:43.25Z"
                    },
                    "uco-observable:endTime": {
                        "@type": "xsd:dateTime",
                        "@value": "2010-01-15T18:30:41.25Z"
                    },
                    "uco-observable:from": {
                        "@id": "kb:phone_account-4e172ed5-7b58-4903-96fe-4558f46820ba"
                    },
                    "uco-observable:to": {
                        "@id": "kb:phone_account-86bdc508-1f64-4df3-bc8f-0136976c2e93"
                    },
                    "uco-observable:duration": 1862
                }
            ]
        },
        {
            "@id": "kb:non-directional-phone-call-d3d321f3-0c47-4ca6-90f7-18697160dcd2",
            "@type": "uco-observable:Call",
            "uco-core:description": "An example of a two-party, one-way phone call that has does not have clear directionality between a caller (from) and receiver (to).",
            "uco-core:hasFacet": [
                {
                    "@id": "kb:call-facet-727322ad-0ef6-4b0b-811c-0f50203d3c73",
                    "@type": "uco-observable:CallFacet",
                    "uco-observable:application": {
                        "@id": "kb:application-79636b28-77c9-4005-b62d-b87a233687ef"
                    },
                    "uco-observable:callType": "outgoing",
                    "uco-observable:startTime": {
                        "@type": "xsd:dateTime",
                        "@value": "2010-01-15T17:59:43.25Z"
                    },
                    "uco-observable:endTime": {
                        "@type": "xsd:dateTime",
                        "@value": "2010-01-15T18:30:41.25Z"
                    },
                    "uco-observable:to": [
                        {
                            "@id": "kb:phone_account-4e172ed5-7b58-4903-96fe-4558f46820ba"
                        },
                        {
                            "@id": "kb:phone_account-86bdc508-1f64-4df3-bc8f-0136976c2e93"
                        }
                    ],
                    "uco-observable:duration": 1862
                }
            ]
        },
        {
            "@id": "kb:multi-participant-phone-call-ce14cf4d-2530-4f8f-9cb6-06f851d1691b",
            "@type": "uco-observable:Call",
            "uco-core:description": "An example of a three-way call phone call that has clear directionality between a caller (from) and two receivers (to).",
            "uco-core:hasFacet": [
                {
                    "@id": "kb:call-facet-5add2a7a-0f44-42dd-a21c-7f60a8862b40",
                    "@type": "uco-observable:CallFacet",
                    "uco-observable:application": {
                        "@id": "kb:application-a5378ee2-32e0-40ba-b31c-3a5c110e7a29"
                    },
                    "uco-observable:callType": "outgoing",
                    "uco-observable:startTime": {
                        "@type": "xsd:dateTime",
                        "@value": "2010-01-15T17:59:43.25Z"
                    },
                    "uco-observable:endTime": {
                        "@type": "xsd:dateTime",
                        "@value": "2010-01-15T18:30:41.25Z"
                    },
                    "uco-observable:from": {
                        "@id": "kb:phone_account-4e172ed5-7b58-4903-96fe-4558f46820ba"
                    },
                    "uco-observable:to": [
                        {
                            "@id": "kb:phone_account-86bdc508-1f64-4df3-bc8f-0136976c2e93"
                        },
                        {
                            "@id": "kb:phone_account-19db8820-3d40-4b38-84cf-abbb26c95128"
                        }
                    ],
                    "uco-observable:duration": 1862
                }
            ]
        },
        {
            "@id": "kb:conference-bridge-phone-call-b3030d8b-ec64-4d88-b136-d4705f657e37",
            "@type": "uco-observable:Call",
            "uco-core:description": "An example of a conference bridge phone call that does not have clear directionality between a caller (from) and receivers (to).",
            "uco-core:hasFacet": [
                {
                    "@id": "kb:call-facet-90ea0dbd-da68-4b90-91b1-f273e29ffc15",
                    "@type": "uco-observable:CallFacet",
                    "uco-observable:application": {
                        "@id": "kb:application-b01d8144-5fa9-44e9-a5f9-668d433b6108"
                    },
                    "uco-observable:callType": "bridge",
                    "uco-observable:startTime": {
                        "@type": "xsd:dateTime",
                        "@value": "2010-01-15T17:59:43.25Z"
                    },
                    "uco-observable:endTime": {
                        "@type": "xsd:dateTime",
                        "@value": "2010-01-15T18:30:41.25Z"
                    },
                    "uco-observable:to": [
                        {
                            "@id": "kb:phone_account-4e172ed5-7b58-4903-96fe-4558f46820ba"
                        },
                        {
                            "@id": "kb:phone_account-86bdc508-1f64-4df3-bc8f-0136976c2e93"
                        },
                        {
                            "@id": "kb:phone_account-19db8820-3d40-4b38-84cf-abbb26c95128"
                        },
                        {
                            "@id": "kb:bridge_account-2ee6c2f5-11dd-42f4-9345-cdefc1e24889"
                        }
                    ],
                    "uco-observable:duration": 1862
                }
            ]
        }
    ]
}
